[{"domain": ".saveonfoods.com", "expiry": 1725568208, "httpOnly": false, "name": "__exponea_time2__", "path": "/", "sameSite": "None", "secure": true, "value": "0.10746121406555176"}, {"domain": ".saveonfoods.com", "expiry": 1760124607, "httpOnly": false, "name": "__exponea_etc__", "path": "/", "sameSite": "None", "secure": true, "value": "684a31d8-075f-4eb6-a1b3-f1274685b238"}, {"domain": ".saveonfoods.com", "expiry": 1759260607, "httpOnly": false, "name": "_uetvid", "path": "/", "sameSite": "Lax", "secure": false, "value": "422724606bbd11efb92885d118d00656"}, {"domain": ".saveonfoods.com", "expiry": 1725651007, "httpOnly": false, "name": "_uetsid", "path": "/", "sameSite": "Lax", "secure": false, "value": "422700006bbd11ef8afd811d43bb64d8"}, {"domain": ".saveonfoods.com", "expiry": 1733340607, "httpOnly": false, "name": "_gcl_au", "path": "/", "sameSite": "Lax", "secure": false, "value": "1.1.1179968847.1725564607"}, {"domain": ".saveonfoods.com", "expiry": 1757100605, "httpOnly": true, "name": "cf_clearance", "path": "/", "sameSite": "None", "secure": true, "value": ".cEHIL50FZXNp9HXN86JwCrLxmqBrVD0gl5Inrr8QYg-1725564605-1.2.1.1-hFkkse2JNwxadBX5AtSIcrN627dUdUmZPCwlLz60ONmLz5yeKq_ZP6IJ.oTVL8S7foSDC6uKZcH7I3V4R8K7FvSTFr93X.19p8a5VqU_FtbqjjeYvEjra.kToWtH5j0OJSZzFMxVTBAuXVHbJpDNwoLYvHIidV4MPobR74NwSS.votKShBXZtAEdin03AXjyPE9MA3I5xavpU4QKO.WO.Czp1.Wbni3Jhl6XfD2Nf9GNY0kLpkFqOAYsQC._MeuMntocWdhkUSxdx61ZxQOeH3iuOaLGWzzkxgNwSdcXdycVjQVK975EvVypYaUCr7AqUSmh5PJWhrUGctxkNJrRF.qu.AdDpiKJ3QFEMH4rmCrvcr1nL16cvZno1cEz1Ezj_Knv_V5caMo5A2hiojf9pg"}, {"domain": ".saveonfoods.com", "expiry": 1757100607, "httpOnly": false, "name": "_pin_unauth", "path": "/", "sameSite": "Lax", "secure": false, "value": "dWlkPU5ETmhaamMzTlRZdE56VTNOQzAwWWpGakxUaGlNVEF0TTJFNU9UTTRNREJoTTJVdw"}, {"domain": ".saveonfoods.com", "expiry": 1760124607, "httpOnly": false, "name": "_ga", "path": "/", "sameSite": "Lax", "secure": false, "value": "GA1.1.2129128356.1725564607"}, {"domain": "www.saveonfoods.com", "expiry": 1728156605, "httpOnly": false, "name": "MI9_RSID", "path": "/", "sameSite": "Lax", "secure": false, "value": "1982"}, {"domain": "www.saveonfoods.com", "expiry": 1728156605, "httpOnly": false, "name": "TIMEOFFSET_COOKIE_NAME", "path": "/", "sameSite": "Lax", "secure": false, "value": "120"}, {"domain": "www.saveonfoods.com", "expiry": 1728156605, "httpOnly": false, "name": "SHOW_PLACEHOLDER_NOTIFICATIONS", "path": "/", "sameSite": "Lax", "secure": false, "value": "false"}, {"domain": ".saveonfoods.com", "expiry": 1733340607, "httpOnly": false, "name": "_fbp", "path": "/", "sameSite": "Lax", "secure": false, "value": "fb.1.1725564607747.983020715630239462"}, {"domain": ".saveonfoods.com", "expiry": 1757100607, "httpOnly": false, "name": "_clck", "path": "/", "sameSite": "Lax", "secure": false, "value": "1im59a1%7C2%7Cfox%7C0%7C1709"}, {"domain": "www.saveonfoods.com", "expiry": 1728156605, "httpOnly": false, "name": "MI9_SHOPPING_MODE", "path": "/", "sameSite": "Lax", "secure": false, "value": "planning"}, {"domain": ".saveonfoods.com", "expiry": 1760124607, "httpOnly": false, "name": "_ga_ZM4WBLPQ9B", "path": "/", "sameSite": "Lax", "secure": false, "value": "GS1.1.1725564607.1.1.1725564607.60.0.0"}, {"domain": ".saveonfoods.com", "expiry": 1725566404, "httpOnly": true, "name": "__cf_bm", "path": "/", "sameSite": "None", "secure": true, "value": ".f4uE5Bj33mvg7.EsDmBhb2CWLjr1Em7vBKYePamI.4-1725564604-1.0.1.1-.gx1VV4ultj00bRnKV9bM6wmhQtOLqdgn0..y4ZhDv79C72CREOrJxrTBaqC1eQ6DEa9BD1GDhOa1ldfqdOfDoXoLEi6hOKOMqbib0Vxyqw"}, {"domain": ".saveonfoods.com", "expiry": 1725651008, "httpOnly": false, "name": "_clsk", "path": "/", "sameSite": "Lax", "secure": false, "value": "jdpmwa%7C1725564608598%7C1%7C1%7Cz.clarity.ms%2Fcollect"}, {"domain": "www.saveonfoods.com", "expiry": 1728156604, "httpOnly": false, "name": "CUSTOMER_SESSION_ID_COOKIE", "path": "/", "sameSite": "Lax", "secure": false, "value": "https://www.saveonfoods.com|6cb7324b-d5fe-462f-a264-351b4d663241"}]