[{"domain": ".novascotia.ca", "expiry": 1725566997, "httpOnly": false, "name": "_gat_UA-29074170-1", "path": "/", "sameSite": "Lax", "secure": false, "value": "1"}, {"domain": ".beta.novascotia.ca", "httpOnly": true, "name": "TS01ad80d5", "path": "/", "sameSite": "Lax", "secure": true, "value": "012df0be5f101a0f2aa36d363adaf66b17320c65358b2ec148b046c6cee1a1841ec1651ade0013c05c925173e2c7542db060915bc9df1babb9dddee172ece6ac4ba4f29ca8"}, {"domain": ".novascotia.ca", "expiry": 1760126937, "httpOnly": false, "name": "_ga", "path": "/", "sameSite": "Lax", "secure": false, "value": "GA1.2.193758590.1725566937"}, {"domain": ".novascotia.ca", "expiry": 1725653337, "httpOnly": false, "name": "_gid", "path": "/", "sameSite": "Lax", "secure": false, "value": "GA1.2.2005218987.1725566937"}, {"domain": ".novascotia.ca", "expiry": 1760126937, "httpOnly": false, "name": "_ga_Z4DW64DX8K", "path": "/", "sameSite": "Lax", "secure": false, "value": "GS1.1.1725566937.1.0.1725566937.60.0.0"}, {"domain": "beta.novascotia.ca", "httpOnly": true, "name": "4c7d3432991026fa0d737c3f7a616f9f", "path": "/", "sameSite": "Lax", "secure": false, "value": "e10b19dd129071812a2b1f895ddaef1c"}, {"domain": ".novascotia.ca", "httpOnly": true, "name": "TS01514ef8", "path": "/", "sameSite": "Lax", "secure": true, "value": "012df0be5f3c0fcc7b4dacbec8f730b3024fb56c78f82624d70fa42c4d5916d8f2ceb97f9726e6209f3bcf641e8bdb84ae19d30f52b65d0de3532d998035fc2c237acc459f"}]