[{"domain": "www.jdsports.co.uk", "expiry": 1757158052, "httpOnly": false, "name": "usersCountry", "path": "/", "sameSite": "Lax", "secure": false, "value": "CA"}, {"domain": "www.jdsports.co.uk", "expiry": 1757165252, "httpOnly": false, "name": "__rtbh.uid", "path": "/", "sameSite": "Lax", "secure": false, "value": "%7B%22eventType%22%3A%22uid%22%2C%22id%22%3A%22undefined%22%7D"}, {"domain": ".jdsports.co.uk", "expiry": 1735990050, "httpOnly": false, "name": "ckgRM", "path": "/", "sameSite": "Lax", "secure": false, "value": "true"}, {"domain": "www.jdsports.co.uk", "httpOnly": true, "name": "akavpau_VP1", "path": "/", "sameSite": "None", "secure": true, "value": "1725622350~id=078c7c9ce49280617b42a48b81ac207a"}, {"domain": "www.jdsports.co.uk", "expiry": 1757165252, "httpOnly": false, "name": "__rtbh.lid", "path": "/", "sameSite": "Lax", "secure": false, "value": "%7B%22eventType%22%3A%22lid%22%2C%22id%22%3A%22fHsF995xdI33ajVVcdtV%22%7D"}, {"domain": "www.jdsports.co.uk", "expiry": 1725708452, "httpOnly": false, "name": "intPopSeen", "path": "/", "sameSite": "Lax", "secure": false, "value": "1"}, {"domain": "www.jdsports.co.uk", "expiry": 1733398049, "httpOnly": false, "name": "49746", "path": "/", "sameSite": "Lax", "secure": false, "value": ""}]